PySide6_Customized_Window.py
PySide6_Customized_Window-1.16.dist-info/METADATA
PySide6_Customized_Window-1.16.dist-info/RECORD
PySide6_Customized_Window-1.16.dist-info/WHEEL
PySide6_Customized_Window-1.16.dist-info/top_level.txt
