Metadata-Version: 2.1
Name: PySide6-Customized-Window
Version: 1.16
Summary: A customized window based on PySide6.
Home-page: https://yuzhouren86.github.io
Author: YuZhouRen86
Author-email: UNKNOWN
License: UNKNOWN
Keywords: Python GUI PySide
Platform: UNKNOWN
Classifier: Programming Language :: Python :: 3
Classifier: Programming Language :: Python :: 2
Classifier: Operating System :: Microsoft :: Windows
Classifier: Development Status :: 5 - Production/Stable
Requires-Python: >=2.6
